{"name":"js lesson02","order":1,"time":"1 hour","helpRoom":"Help","language":"js","description":["\u6587\u5b57\u306e\u51fa\u529b \u30a2\u30e9\u30fc\u30c8\u3092\u3042\u3052\u308b","document.write\u3001confirm\u306a\u3069\u306e\u6587\u5b57\u5217\u306a\u3069\u306e\u51fa\u529b\u65b9\u6cd5\u3084\u30b3\u30e1\u30f3\u30c8\u306e\u65b9\u6cd5\u3092\u5b66\u3073\u307e\u3059\u3002"],"challenges":[{"id":"5ad5ab8eeceaedf7323792a3","title":"js-2-1","description":["\u6587\u5b57\u306e\u51fa\u529b \u30a2\u30e9\u30fc\u30c8\u3092\u3042\u3052\u308b","document.write\u3001confirm\u306a\u3069\u306e\u6587\u5b57\u5217\u306a\u3069\u306e\u51fa\u529b\u65b9\u6cd5\u3084\u30b3\u30e1\u30f3\u30c8\u306e\u65b9\u6cd5\u3092\u5b66\u3073\u307e\u3059\u3002"],"challengeSeed":["https:\/\/player.vimeo.com\/video\/231854245"],"tests":[],"type":"hike","solutions":[],"challengeType":8,"translations":{}},{"id":"5ad5ab8eeceaedf7323792a4","title":"js-2-2","description":["\u6587\u5b57\u306e\u51fa\u529b \u30a2\u30e9\u30fc\u30c8\u3092\u3042\u3052\u308b","document.write\u3001confirm\u306a\u3069\u306e\u6587\u5b57\u5217\u306a\u3069\u306e\u51fa\u529b\u65b9\u6cd5\u3084\u30b3\u30e1\u30f3\u30c8\u306e\u65b9\u6cd5\u3092\u5b66\u3073\u307e\u3059\u3002"],"challengeSeed":["https:\/\/onedrive.live.com\/embed?cid=43A9521829D9F012&resid=43A9521829D9F012%21147&authkey=AD0PXfA-GKQd-Gw&em=2"],"tests":[],"type":"hike","solutions":[],"challengeType":8,"translations":{}},{"id":"5ad5ab8eeceaedf7323792a5","title":"js-2-3","description":["\u6587\u5b57\u306e\u51fa\u529b \u30a2\u30e9\u30fc\u30c8\u3092\u3042\u3052\u308b","document.write\u3001confirm\u306a\u3069\u306e\u6587\u5b57\u5217\u306a\u3069\u306e\u51fa\u529b\u65b9\u6cd5\u3084\u30b3\u30e1\u30f3\u30c8\u306e\u65b9\u6cd5\u3092\u5b66\u3073\u307e\u3059\u3002"],"language":"js","javaClass":"Main","codeInputs":[{"title":"\u30a8\u30c7\u30a3\u30bf(index.html)","contents":["<body>","","<script src=\"script.js\"><\/script>","","<\/body>","<\/html>"],"ext":"html","name":"index"},{"title":"\u30a8\u30c7\u30a3\u30bf(script.js)","contents":[""],"ext":"js","name":"index"}],"codeModels":[{"title":"HTML \u5199\u7d4c\u30c6\u30ad\u30b9\u30c8","contents":["<body>","","<script src=\"script.js\"><\/script>","","<\/body>","<\/html>"]},{"title":"JavaScript \u5199\u7d4c\u30c6\u30ad\u30b9\u30c8","contents":["document.write(\"document.write\u3067\u3001\u6587\u5b57\u5217\u3092\u51fa\u529b\u3057\u307e\u3059\u3002\");"]}],"tests":[],"type":"waypoint","solutions":[],"challengeType":11,"translations":{}},{"id":"5ad5ab8eeceaedf7323792a6","title":"js-2-4","description":["\u6587\u5b57\u306e\u51fa\u529b \u30a2\u30e9\u30fc\u30c8\u3092\u3042\u3052\u308b","document.write\u3001confirm\u306a\u3069\u306e\u6587\u5b57\u5217\u306a\u3069\u306e\u51fa\u529b\u65b9\u6cd5\u3084\u30b3\u30e1\u30f3\u30c8\u306e\u65b9\u6cd5\u3092\u5b66\u3073\u307e\u3059\u3002"],"language":"js","javaClass":"Main","codeInputs":[{"title":"\u30a8\u30c7\u30a3\u30bf(index.html)","contents":["<body>","","<script src=\"script.js\"><\/script>","","<\/body>","<\/html>"],"ext":"html","name":"index"},{"title":"\u30a8\u30c7\u30a3\u30bf(script.js)","contents":[""],"ext":"js","name":"index"}],"codeModels":[{"title":"HTML \u5199\u7d4c\u30c6\u30ad\u30b9\u30c8","contents":["<body>","","<script src=\"script.js\"><\/script>","","<\/body>","<\/html>"]},{"title":"JavaScript \u5199\u7d4c\u30c6\u30ad\u30b9\u30c8","contents":["document.write(\"\u3042\u3044\u3046\u3048\u304a\");"]}],"tests":[],"type":"waypoint","solutions":[],"challengeType":11,"translations":{}},{"id":"5ad5ab8eeceaedf7323792a7","title":"js-2-5","description":["\u6587\u5b57\u306e\u51fa\u529b \u30a2\u30e9\u30fc\u30c8\u3092\u3042\u3052\u308b","document.write\u3001confirm\u306a\u3069\u306e\u6587\u5b57\u5217\u306a\u3069\u306e\u51fa\u529b\u65b9\u6cd5\u3084\u30b3\u30e1\u30f3\u30c8\u306e\u65b9\u6cd5\u3092\u5b66\u3073\u307e\u3059\u3002"],"language":"js","javaClass":"Main","codeInputs":[{"title":"\u30a8\u30c7\u30a3\u30bf(index.html)","contents":["<body>","","<script src=\"script.js\"><\/script>","","<\/body>","<\/html>"],"ext":"html","name":"index"},{"title":"\u30a8\u30c7\u30a3\u30bf(script.js)","contents":[""],"ext":"js","name":"index"}],"codeModels":[{"title":"HTML \u5199\u7d4c\u30c6\u30ad\u30b9\u30c8","contents":["<body>","","<script src=\"script.js\"><\/script>","","<\/body>","<\/html>"]},{"title":"JavaScript \u5199\u7d4c\u30c6\u30ad\u30b9\u30c8","contents":["document.write(\"Hello World\");"]}],"tests":[],"type":"waypoint","solutions":[],"challengeType":11,"translations":{}},{"id":"5ad5ab8eeceaedf7323792a8","title":"js-2-6","description":["\u6587\u5b57\u306e\u51fa\u529b \u30a2\u30e9\u30fc\u30c8\u3092\u3042\u3052\u308b","document.write\u3001confirm\u306a\u3069\u306e\u6587\u5b57\u5217\u306a\u3069\u306e\u51fa\u529b\u65b9\u6cd5\u3084\u30b3\u30e1\u30f3\u30c8\u306e\u65b9\u6cd5\u3092\u5b66\u3073\u307e\u3059\u3002"],"language":"js","javaClass":"Main","codeInputs":[{"title":"\u30a8\u30c7\u30a3\u30bf(index.html)","contents":["<body>","","<script src=\"script.js\"><\/script>","","<\/body>","<\/html>"],"ext":"html","name":"index"},{"title":"\u30a8\u30c7\u30a3\u30bf(script.js)","contents":[""],"ext":"js","name":"index"}],"codeModels":[{"title":"HTML \u5199\u7d4c\u30c6\u30ad\u30b9\u30c8","contents":["<body>","","<script src=\"script.js\"><\/script>","","<\/body>","<\/html>"]},{"title":"JavaScript \u5199\u7d4c\u30c6\u30ad\u30b9\u30c8","contents":["alert(\"alert\u3067\u3001\u30a2\u30e9\u30fc\u30c8\u3092\u8868\u793a\u3057\u307e\u3059\u3002\");"]}],"tests":[],"type":"waypoint","solutions":[],"challengeType":11,"translations":{}},{"id":"5ad5ab8eeceaedf7323792a9","title":"js-2-7","description":["\u6587\u5b57\u306e\u51fa\u529b \u30a2\u30e9\u30fc\u30c8\u3092\u3042\u3052\u308b","document.write\u3001confirm\u306a\u3069\u306e\u6587\u5b57\u5217\u306a\u3069\u306e\u51fa\u529b\u65b9\u6cd5\u3084\u30b3\u30e1\u30f3\u30c8\u306e\u65b9\u6cd5\u3092\u5b66\u3073\u307e\u3059\u3002"],"language":"js","javaClass":"Main","codeInputs":[{"title":"\u30a8\u30c7\u30a3\u30bf(index.html)","contents":["<body>","","<script src=\"script.js\"><\/script>","","<\/body>","<\/html>"],"ext":"html","name":"index"},{"title":"\u30a8\u30c7\u30a3\u30bf(script.js)","contents":[""],"ext":"js","name":"index"}],"codeModels":[{"title":"HTML \u5199\u7d4c\u30c6\u30ad\u30b9\u30c8","contents":["<body>","","<script src=\"script.js\"><\/script>","","<\/body>","<\/html>"]},{"title":"JavaScript \u5199\u7d4c\u30c6\u30ad\u30b9\u30c8","contents":["alert(\"\u5225\u306e\u30da\u30fc\u30b8\u306b\u79fb\u52d5\u3057\u3088\u3046\u3068\u3057\u3066\u3044\u307e\u3059\uff01\");"]}],"tests":[],"type":"waypoint","solutions":[],"challengeType":11,"translations":{}},{"id":"5ad5ab8eeceaedf7323792aa","title":"js-2-8","description":["\u6587\u5b57\u306e\u51fa\u529b \u30a2\u30e9\u30fc\u30c8\u3092\u3042\u3052\u308b","document.write\u3001confirm\u306a\u3069\u306e\u6587\u5b57\u5217\u306a\u3069\u306e\u51fa\u529b\u65b9\u6cd5\u3084\u30b3\u30e1\u30f3\u30c8\u306e\u65b9\u6cd5\u3092\u5b66\u3073\u307e\u3059\u3002"],"language":"js","javaClass":"Main","codeInputs":[{"title":"\u30a8\u30c7\u30a3\u30bf(index.html)","contents":["<body>","","<script src=\"script.js\"><\/script>","","<\/body>","<\/html>"],"ext":"html","name":"index"},{"title":"\u30a8\u30c7\u30a3\u30bf(script.js)","contents":[""],"ext":"js","name":"index"}],"codeModels":[{"title":"HTML \u5199\u7d4c\u30c6\u30ad\u30b9\u30c8","contents":["<body>","","<script src=\"script.js\"><\/script>","","<\/body>","<\/html>"]},{"title":"JavaScript \u5199\u7d4c\u30c6\u30ad\u30b9\u30c8","contents":["alert(\"\u672a\u5165\u529b\u306e\u9805\u76ee\u304c\u3042\u308a\u307e\u3059\u3002\");"]}],"tests":[],"type":"waypoint","solutions":[],"challengeType":11,"translations":{}},{"id":"5ad5ab8eeceaedf7323792ab","title":"js-2-9","description":["\u6587\u5b57\u306e\u51fa\u529b \u30a2\u30e9\u30fc\u30c8\u3092\u3042\u3052\u308b","document.write\u3001confirm\u306a\u3069\u306e\u6587\u5b57\u5217\u306a\u3069\u306e\u51fa\u529b\u65b9\u6cd5\u3084\u30b3\u30e1\u30f3\u30c8\u306e\u65b9\u6cd5\u3092\u5b66\u3073\u307e\u3059\u3002"],"language":"js","javaClass":"Main","codeInputs":[{"title":"\u30a8\u30c7\u30a3\u30bf(index.html)","contents":["<body>","","<script src=\"script.js\"><\/script>","","<\/body>","<\/html>"],"ext":"html","name":"index"},{"title":"\u30a8\u30c7\u30a3\u30bf(script.js)","contents":[""],"ext":"js","name":"index"}],"codeModels":[{"title":"HTML \u5199\u7d4c\u30c6\u30ad\u30b9\u30c8","contents":["<body>","","<script src=\"script.js\"><\/script>","","<\/body>","<\/html>"]},{"title":"JavaScript \u5199\u7d4c\u30c6\u30ad\u30b9\u30c8","contents":["confirm(\"confirm\u3067\u3001\u78ba\u8a8d\u30c0\u30a4\u30a2\u30ed\u30b0\u3092\u8868\u793a\u3057\u307e\u3059\u3002\");"]}],"tests":[],"type":"waypoint","solutions":[],"challengeType":11,"translations":{}},{"id":"5ad5ab8eeceaedf7323792ac","title":"js-2-10","description":["\u6587\u5b57\u306e\u51fa\u529b \u30a2\u30e9\u30fc\u30c8\u3092\u3042\u3052\u308b","document.write\u3001confirm\u306a\u3069\u306e\u6587\u5b57\u5217\u306a\u3069\u306e\u51fa\u529b\u65b9\u6cd5\u3084\u30b3\u30e1\u30f3\u30c8\u306e\u65b9\u6cd5\u3092\u5b66\u3073\u307e\u3059\u3002"],"language":"js","javaClass":"Main","codeInputs":[{"title":"\u30a8\u30c7\u30a3\u30bf(index.html)","contents":["<body>","","<script src=\"script.js\"><\/script>","","<\/body>","<\/html>"],"ext":"html","name":"index"},{"title":"\u30a8\u30c7\u30a3\u30bf(script.js)","contents":[""],"ext":"js","name":"index"}],"codeModels":[{"title":"HTML \u5199\u7d4c\u30c6\u30ad\u30b9\u30c8","contents":["<body>","","<script src=\"script.js\"><\/script>","","<\/body>","<\/html>"]},{"title":"JavaScript \u5199\u7d4c\u30c6\u30ad\u30b9\u30c8","contents":["confirm(\"\u5165\u529b\u3092\u78ba\u5b9a\u3057\u3066\u3082\u3088\u308d\u3057\u3044\u3067\u3057\u3087\u3046\u304b\uff1f\");"]}],"tests":[],"type":"waypoint","solutions":[],"challengeType":11,"translations":{}},{"id":"5ad5ab8eeceaedf7323792ad","title":"js-2-11","description":["\u6587\u5b57\u306e\u51fa\u529b \u30a2\u30e9\u30fc\u30c8\u3092\u3042\u3052\u308b","document.write\u3001confirm\u306a\u3069\u306e\u6587\u5b57\u5217\u306a\u3069\u306e\u51fa\u529b\u65b9\u6cd5\u3084\u30b3\u30e1\u30f3\u30c8\u306e\u65b9\u6cd5\u3092\u5b66\u3073\u307e\u3059\u3002"],"language":"js","javaClass":"Main","codeInputs":[{"title":"\u30a8\u30c7\u30a3\u30bf(index.html)","contents":["<body>","","<script src=\"script.js\"><\/script>","","<\/body>","<\/html>"],"ext":"html","name":"index"},{"title":"\u30a8\u30c7\u30a3\u30bf(script.js)","contents":[""],"ext":"js","name":"index"}],"codeModels":[{"title":"HTML \u5199\u7d4c\u30c6\u30ad\u30b9\u30c8","contents":["<body>","","<script src=\"script.js\"><\/script>","","<\/body>","<\/html>"]},{"title":"JavaScript \u5199\u7d4c\u30c6\u30ad\u30b9\u30c8","contents":["confirm(\"\u30da\u30fc\u30b8\u3092\u79fb\u52d5\u3057\u307e\u3059\u3002\");"]}],"tests":[],"type":"waypoint","solutions":[],"challengeType":11,"translations":{}},{"id":"5ad5ab8eeceaedf7323792ae","title":"js-2-12","description":["\u6587\u5b57\u306e\u51fa\u529b \u30a2\u30e9\u30fc\u30c8\u3092\u3042\u3052\u308b","document.write\u3001confirm\u306a\u3069\u306e\u6587\u5b57\u5217\u306a\u3069\u306e\u51fa\u529b\u65b9\u6cd5\u3084\u30b3\u30e1\u30f3\u30c8\u306e\u65b9\u6cd5\u3092\u5b66\u3073\u307e\u3059\u3002"],"language":"js","javaClass":null,"codeInputs":[{"title":"\u30a8\u30c7\u30a3\u30bf(index.html)","ext":"html","name":"index","contents":["<body>","","<script src=\"script.js\"><\/script>","","<\/body>","<\/html>"]},{"title":"\u30a8\u30c7\u30a3\u30bf(script.js)","ext":"js","name":"index","contents":["document.write(\"XXXX\");"]}],"codeModels":[{"title":"\u554f\u984c","contents":["<index.html>","\u5909\u66f4\u306a\u3057","","<script.js>","\u300c\u3053\u3093\u306b\u3061\u306f\u300d\u3068\u51fa\u529b\u3067\u304d\u308b\u3088\u3046\u306bXXXX\u3092\u5909\u66f4\u3057\u3066\u304f\u3060\u3055\u3044\u3002"]}],"tests":[],"type":"waypoint","solutions":[],"challengeType":9,"translations":{}},{"id":"5ad5ab8eeceaedf7323792af","title":"js-2-13","description":["\u6587\u5b57\u306e\u51fa\u529b \u30a2\u30e9\u30fc\u30c8\u3092\u3042\u3052\u308b","document.write\u3001confirm\u306a\u3069\u306e\u6587\u5b57\u5217\u306a\u3069\u306e\u51fa\u529b\u65b9\u6cd5\u3084\u30b3\u30e1\u30f3\u30c8\u306e\u65b9\u6cd5\u3092\u5b66\u3073\u307e\u3059\u3002"],"language":"js","javaClass":null,"codeInputs":[{"title":"\u30a8\u30c7\u30a3\u30bf(index.html)","ext":"html","name":"index","contents":["<body>","","<script src=\"script.js\"><\/script>","","<\/body>","<\/html>"]},{"title":"\u30a8\u30c7\u30a3\u30bf(script.js)","ext":"js","name":"index","contents":["XXXX(\"welcome!\");"]}],"codeModels":[{"title":"\u554f\u984c","contents":["<index.html>","\u5909\u66f4\u306a\u3057","","<script.js>","\u300c welcome! \u300d\u3068\u51fa\u529b\u3067\u304d\u308b\u3088\u3046\u306bXXXX\u3092\u5909\u66f4\u3057\u3066\u304f\u3060\u3055\u3044\u3002"]}],"tests":[],"type":"waypoint","solutions":[],"challengeType":9,"translations":{}},{"id":"5ad5ab8eeceaedf7323792b0","title":"js-2-14","description":["\u6587\u5b57\u306e\u51fa\u529b \u30a2\u30e9\u30fc\u30c8\u3092\u3042\u3052\u308b","document.write\u3001confirm\u306a\u3069\u306e\u6587\u5b57\u5217\u306a\u3069\u306e\u51fa\u529b\u65b9\u6cd5\u3084\u30b3\u30e1\u30f3\u30c8\u306e\u65b9\u6cd5\u3092\u5b66\u3073\u307e\u3059\u3002"],"language":"js","javaClass":null,"codeInputs":[{"title":"\u30a8\u30c7\u30a3\u30bf(index.html)","ext":"html","name":"index","contents":["<body>","","<script src=\"script.js\"><\/script>","","<\/body>","<\/html>"]},{"title":"\u30a8\u30c7\u30a3\u30bf(script.js)","ext":"js","name":"index","contents":["\"XXXX\""]}],"codeModels":[{"title":"\u554f\u984c","contents":["<index.html>","\u5909\u66f4\u306a\u3057","","<script.js>","\u300c\u6587\u5b57\u5217\u3092\u51fa\u529b\u3057\u307e\u3059\u3002\u300d\u3068\u51fa\u529b\u3067\u304d\u308b\u3088\u3046\u306bXXXX\u3092\u5909\u66f4\u3057\u3066\u304f\u3060\u3055\u3044\u3002"]}],"tests":[],"type":"waypoint","solutions":[],"challengeType":9,"translations":{}},{"id":"5ad5ab8eeceaedf7323792b1","title":"js-2-15","description":["\u6587\u5b57\u306e\u51fa\u529b \u30a2\u30e9\u30fc\u30c8\u3092\u3042\u3052\u308b","document.write\u3001confirm\u306a\u3069\u306e\u6587\u5b57\u5217\u306a\u3069\u306e\u51fa\u529b\u65b9\u6cd5\u3084\u30b3\u30e1\u30f3\u30c8\u306e\u65b9\u6cd5\u3092\u5b66\u3073\u307e\u3059\u3002"],"language":"js","javaClass":null,"codeInputs":[{"title":"\u30a8\u30c7\u30a3\u30bf(index.html)","ext":"html","name":"index","contents":["<body>","","<script src=\"script.js\"><\/script>","","<\/body>","<\/html>"]},{"title":"\u30a8\u30c7\u30a3\u30bf(script.js)","ext":"js","name":"index","contents":["alert(\"XXXX\");"]}],"codeModels":[{"title":"\u554f\u984c","contents":["<index.html>","\u5909\u66f4\u306a\u3057","","<script.js>","\u300c\u3042\u3044\u3046\u3048\u304a\u300d\u3068\u30a2\u30e9\u30fc\u30c8\u304c\u8868\u793a\u3067\u304d\u308b\u3088\u3046\u306bXXXX\u3092\u5909\u66f4\u3057\u3066\u304f\u3060\u3055\u3044\u3002"]}],"tests":[],"type":"waypoint","solutions":[],"challengeType":9,"translations":{}},{"id":"5ad5ab8eeceaedf7323792b2","title":"js-2-16","description":["\u6587\u5b57\u306e\u51fa\u529b \u30a2\u30e9\u30fc\u30c8\u3092\u3042\u3052\u308b","document.write\u3001confirm\u306a\u3069\u306e\u6587\u5b57\u5217\u306a\u3069\u306e\u51fa\u529b\u65b9\u6cd5\u3084\u30b3\u30e1\u30f3\u30c8\u306e\u65b9\u6cd5\u3092\u5b66\u3073\u307e\u3059\u3002"],"language":"js","javaClass":null,"codeInputs":[{"title":"\u30a8\u30c7\u30a3\u30bf(index.html)","ext":"html","name":"index","contents":["<body>","","<script src=\"script.js\"><\/script>","","<\/body>","<\/html>"]},{"title":"\u30a8\u30c7\u30a3\u30bf(script.js)","ext":"js","name":"index","contents":["XXXX(\"\u30a8\u30e9\u30fc\u304c\u3042\u308a\u307e\u3059\u3002\");"]}],"codeModels":[{"title":"\u554f\u984c","contents":["<index.html>","\u5909\u66f4\u306a\u3057","","<script.js>","\u300c\u30a8\u30e9\u30fc\u304c\u3042\u308a\u307e\u3059\u3002\u300d\u3068\u30a2\u30e9\u30fc\u30c8\u304c\u8868\u793a\u3067\u304d\u308b\u3088\u3046\u306bXXXX\u3092\u5909\u66f4\u3057\u3066\u304f\u3060\u3055\u3044\u3002"]}],"tests":[],"type":"waypoint","solutions":[],"challengeType":9,"translations":{}},{"id":"5ad5ab8eeceaedf7323792b3","title":"js-2-17","description":["\u6587\u5b57\u306e\u51fa\u529b \u30a2\u30e9\u30fc\u30c8\u3092\u3042\u3052\u308b","document.write\u3001confirm\u306a\u3069\u306e\u6587\u5b57\u5217\u306a\u3069\u306e\u51fa\u529b\u65b9\u6cd5\u3084\u30b3\u30e1\u30f3\u30c8\u306e\u65b9\u6cd5\u3092\u5b66\u3073\u307e\u3059\u3002"],"language":"js","javaClass":null,"codeInputs":[{"title":"\u30a8\u30c7\u30a3\u30bf(index.html)","ext":"html","name":"index","contents":["<body>","","<script src=\"script.js\"><\/script>","","<\/body>","<\/html>"]},{"title":"\u30a8\u30c7\u30a3\u30bf(script.js)","ext":"js","name":"index","contents":["XXXX"]}],"codeModels":[{"title":"\u554f\u984c","contents":["<index.html>","\u5909\u66f4\u306a\u3057","","<script.js>","\u300c\u5fc5\u9808\u9805\u76ee\u304c\u672a\u5165\u529b\u3067\u3059\u300d\u3068\u30a2\u30e9\u30fc\u30c8\u304c\u8868\u793a\u3067\u304d\u308b\u3088\u3046\u306bXXXX\u3092\u5909\u66f4\u3057\u3066\u304f\u3060\u3055\u3044\u3002"]}],"tests":[],"type":"waypoint","solutions":[],"challengeType":9,"translations":{}},{"id":"5ad5ab8eeceaedf7323792b4","title":"js-2-18","description":["\u6587\u5b57\u306e\u51fa\u529b \u30a2\u30e9\u30fc\u30c8\u3092\u3042\u3052\u308b","document.write\u3001confirm\u306a\u3069\u306e\u6587\u5b57\u5217\u306a\u3069\u306e\u51fa\u529b\u65b9\u6cd5\u3084\u30b3\u30e1\u30f3\u30c8\u306e\u65b9\u6cd5\u3092\u5b66\u3073\u307e\u3059\u3002"],"language":"js","javaClass":null,"codeInputs":[{"title":"\u30a8\u30c7\u30a3\u30bf(index.html)","ext":"html","name":"index","contents":["<body>","","<script src=\"script.js\"><\/script>","","<\/body>","<\/html>"]},{"title":"\u30a8\u30c7\u30a3\u30bf(script.js)","ext":"js","name":"index","contents":["confirm(\"XXXX\");"]}],"codeModels":[{"title":"\u554f\u984c","contents":["<index.html>","\u5909\u66f4\u306a\u3057","","<script.js>","\u300c\u30da\u30fc\u30b8\u3092\u79fb\u52d5\u3057\u3066\u3082\u3088\u308d\u3057\u3044\u3067\u3059\u304b\uff1f \u300d\u3068\u78ba\u8a8d\u30c0\u30a4\u30a2\u30ed\u30b0\u304c\u8868\u793a\u3067\u304d\u308b\u3088\u3046\u306bXXXX\u3092\u5909\u66f4\u3057\u3066\u304f\u3060\u3055\u3044\u3002"]}],"tests":[],"type":"waypoint","solutions":[],"challengeType":9,"translations":{}},{"id":"5ad5ab8eeceaedf7323792b5","title":"js-2-19","description":["\u6587\u5b57\u306e\u51fa\u529b \u30a2\u30e9\u30fc\u30c8\u3092\u3042\u3052\u308b","document.write\u3001confirm\u306a\u3069\u306e\u6587\u5b57\u5217\u306a\u3069\u306e\u51fa\u529b\u65b9\u6cd5\u3084\u30b3\u30e1\u30f3\u30c8\u306e\u65b9\u6cd5\u3092\u5b66\u3073\u307e\u3059\u3002"],"language":"js","javaClass":null,"codeInputs":[{"title":"\u30a8\u30c7\u30a3\u30bf(index.html)","ext":"html","name":"index","contents":["<body>","","<script src=\"script.js\"><\/script>","","<\/body>","<\/html>"]},{"title":"\u30a8\u30c7\u30a3\u30bf(script.js)","ext":"js","name":"index","contents":["XXXX(\"\u5165\u529b\u9805\u76ee\u3092\u521d\u671f\u5316\u3057\u307e\u3059\u3002\");"]}],"codeModels":[{"title":"\u554f\u984c","contents":["<index.html>","\u5909\u66f4\u306a\u3057","","<script.js>","\u300c\u5165\u529b\u9805\u76ee\u3092\u521d\u671f\u5316\u3057\u307e\u3059\u3002 \u300d\u3068\u78ba\u8a8d\u30c0\u30a4\u30a2\u30ed\u30b0\u304c\u8868\u793a\u3067\u304d\u308b\u3088\u3046\u306bXXXX\u3092\u5909\u66f4\u3057\u3066\u304f\u3060\u3055\u3044\u3002"]}],"tests":[],"type":"waypoint","solutions":[],"challengeType":9,"translations":{}},{"id":"5ad5ab8eeceaedf7323792b6","title":"js-2-20","description":["\u6587\u5b57\u306e\u51fa\u529b \u30a2\u30e9\u30fc\u30c8\u3092\u3042\u3052\u308b","document.write\u3001confirm\u306a\u3069\u306e\u6587\u5b57\u5217\u306a\u3069\u306e\u51fa\u529b\u65b9\u6cd5\u3084\u30b3\u30e1\u30f3\u30c8\u306e\u65b9\u6cd5\u3092\u5b66\u3073\u307e\u3059\u3002"],"language":"js","javaClass":null,"codeInputs":[{"title":"\u30a8\u30c7\u30a3\u30bf(index.html)","ext":"html","name":"index","contents":["<body>","","<script src=\"script.js\"><\/script>","","<\/body>","<\/html>"]},{"title":"\u30a8\u30c7\u30a3\u30bf(script.js)","ext":"js","name":"index","contents":["XXXX"]}],"codeModels":[{"title":"\u554f\u984c","contents":["<index.html>","\u5909\u66f4\u306a\u3057","","<script.js>","\u300c\u51e6\u7406\u3092\u958b\u59cb\u3057\u307e\u3059\u3002\u300d\u3068\u78ba\u8a8d\u30c0\u30a4\u30a2\u30ed\u30b0\u304c\u8868\u793a\u3067\u304d\u308b\u3088\u3046\u306bXXXX\u3092\u5909\u66f4\u3057\u3066\u304f\u3060\u3055\u3044\u3002"]}],"tests":[],"type":"waypoint","solutions":[],"challengeType":9,"translations":{}}]}